GUI/chameleon_iq.py
chameleoniq-2.0.0.dist-info/licenses/LICENSE.txt
config/__init__.py
config/defaults.py
nema_merge/__init__.py
nema_merge/__main__.py
nema_merge/cli.py
nema_merge/reporting.py
nema_quant/__init__.py
nema_quant/__main__.py
nema_quant/analysis.py
nema_quant/cli.py
nema_quant/interactive_roi_editor.py
nema_quant/io.py
nema_quant/metrics.py
nema_quant/phantom.py
nema_quant/reporting.py
nema_quant/utils.py
nema_quant_iter/__init__.py
nema_quant_iter/__main__.py
nema_quant_iter/cli.py
nema_quant_iter/reporting.py
chameleoniq-2.0.0.dist-info/METADATA
chameleoniq-2.0.0.dist-info/WHEEL
chameleoniq-2.0.0.dist-info/entry_points.txt
chameleoniq-2.0.0.dist-info/top_level.txt
chameleoniq-2.0.0.dist-info/RECORD
