Metadata-Version: 2.4
Name: ChameleonIQ
Version: 2.0.0
Summary: A tool for NEMA NU 2-2018 Image Quality analysis.
Author: Edwing Ulin-Briseno
Author-email: EdAlita <eyulibri@i3m.upv.es>
License-Expression: MIT AND (Apache-2.0 OR BSD-2-Clause)
Project-URL: Homepage, https://github.com/EdAlita/ChameleonIQ/wiki
Project-URL: GitHub, https://github.com/EdAlita/ChameleonIQ
Project-URL: Changelog, https://github.com/EdAlita/ChameleonIQ/wiki/Changelog
Project-URL: Issues, https://github.com/EdAlita/ChameleonIQ/issues
Project-URL: Download, https://pypi.org/project/ChameleonIQ/#files
Platform: unix
Platform: linux
Platform: osx
Platform: cygwin
Platform: win32
Classifier: Programming Language :: Python :: 3.12
Classifier: Programming Language :: Python :: 3.11
Classifier: Development Status :: 5 - Production/Stable
Classifier: Environment :: Console
Classifier: Operating System :: OS Independent
Classifier: Intended Audience :: Healthcare Industry
Classifier: Natural Language :: English
Classifier: Topic :: Scientific/Engineering :: Medical Science Apps.
Requires-Python: >=3.11
License-File: LICENSE.txt
Requires-Dist: numpy==2.2.6
Requires-Dist: scipy==1.16.0
Requires-Dist: scipy-stubs==1.16.0.2
Requires-Dist: nibabel==5.3.2
Requires-Dist: matplotlib==3.10.3
Requires-Dist: seaborn==0.13.2
Requires-Dist: pandas==2.3.1
Requires-Dist: yacs==0.1.8
Requires-Dist: opencv-python==4.12.0.88
Requires-Dist: pillow==11.3.0
Requires-Dist: reportlab==4.4.2
Requires-Dist: types-reportlab==4.4.1.20250602
Requires-Dist: SimpleITK==2.5.2
Requires-Dist: scikit-image==0.25.2
Requires-Dist: rich==14.2.0
Requires-Dist: statsmodels==0.14.5
Requires-Dist: PyQt5==5.15.11
Provides-Extra: dev
Requires-Dist: pytest==8.4.1; extra == "dev"
Requires-Dist: pytest-cov==6.2.1; extra == "dev"
Requires-Dist: mypy==1.16.1; extra == "dev"
Requires-Dist: mypy_extensions==1.1.0; extra == "dev"
Requires-Dist: flake8==7.3.0; extra == "dev"
Dynamic: license-file
